[{"cat":"Coffee","dscr":"With choices of serving and topping available","icon":"https:\/\/raw.githubusercontent.com\/jalajoninc\/tha\/main\/chiang-mai\/nuch-coffee\/3225880.jpg","image":"https:\/\/images.deliveryhero.io\/image\/fd-th\/Products\/3225880.jpg","item":"Nescafe","price":"30"},{"cat":"Coffee","dscr":"With choices of serving and topping available","icon":"https:\/\/raw.githubusercontent.com\/jalajoninc\/tha\/main\/chiang-mai\/nuch-coffee\/3225880.jpg","image":"https:\/\/images.deliveryhero.io\/image\/fd-th\/Products\/3225880.jpg","item":"Cappuccino","price":"30"},{"cat":"Coffee","dscr":"With choices of serving and topping available","icon":"https:\/\/raw.githubusercontent.com\/jalajoninc\/tha\/main\/chiang-mai\/nuch-coffee\/3225880.jpg","image":"https:\/\/images.deliveryhero.io\/image\/fd-th\/Products\/3225880.jpg","item":"Latte","price":"30"},{"cat":"Coffee","dscr":"With choices of serving and topping available","icon":"https:\/\/raw.githubusercontent.com\/jalajoninc\/tha\/main\/chiang-mai\/nuch-coffee\/3225880.jpg","image":"https:\/\/images.deliveryhero.io\/image\/fd-th\/Products\/3225880.jpg","item":"Mocha","price":"30"},{"cat":"Coffee","dscr":"With choices of serving and topping available","icon":"https:\/\/raw.githubusercontent.com\/jalajoninc\/tha\/main\/chiang-mai\/nuch-coffee\/3225880.jpg","image":"https:\/\/images.deliveryhero.io\/image\/fd-th\/Products\/3225880.jpg","item":"Espresso","price":"30"},{"cat":"Milk","dscr":"With choices of serving and topping available","icon":"https:\/\/raw.githubusercontent.com\/jalajoninc\/tha\/main\/chiang-mai\/nuch-coffee\/3225880.jpg","image":"https:\/\/images.deliveryhero.io\/image\/fd-th\/Products\/3225880.jpg","item":"Pink Milk","price":"30"},{"cat":"Milk","dscr":"With choices of serving and topping available","icon":"https:\/\/raw.githubusercontent.com\/jalajoninc\/tha\/main\/chiang-mai\/nuch-coffee\/3225880.jpg","image":"https:\/\/images.deliveryhero.io\/image\/fd-th\/Products\/3225880.jpg","item":"Fresh Milk","price":"30"},{"cat":"Milk","dscr":"With choices of serving and topping available","icon":"https:\/\/raw.githubusercontent.com\/jalajoninc\/tha\/main\/chiang-mai\/nuch-coffee\/3225880.jpg","image":"https:\/\/images.deliveryhero.io\/image\/fd-th\/Products\/3225880.jpg","item":"Honey Milk","price":"30"},{"cat":"Milk","dscr":"With choices of serving and topping available","icon":"https:\/\/raw.githubusercontent.com\/jalajoninc\/tha\/main\/chiang-mai\/nuch-coffee\/3225880.jpg","image":"https:\/\/images.deliveryhero.io\/image\/fd-th\/Products\/3225880.jpg","item":"Oreo Milk","price":"30"},{"cat":"Milk","dscr":"With choices of serving and topping available","icon":"https:\/\/raw.githubusercontent.com\/jalajoninc\/tha\/main\/chiang-mai\/nuch-coffee\/3225880.jpg","image":"https:\/\/images.deliveryhero.io\/image\/fd-th\/Products\/3225880.jpg","item":"Cocoa","price":"30"},{"cat":"Milk","dscr":"With choices of serving and topping available","icon":"https:\/\/raw.githubusercontent.com\/jalajoninc\/tha\/main\/chiang-mai\/nuch-coffee\/3225880.jpg","image":"https:\/\/images.deliveryhero.io\/image\/fd-th\/Products\/3225880.jpg","item":"Ovaltine","price":"30"},{"cat":"Milk","dscr":"With choices of serving and topping available","icon":"https:\/\/raw.githubusercontent.com\/jalajoninc\/tha\/main\/chiang-mai\/nuch-coffee\/3225880.jpg","image":"https:\/\/images.deliveryhero.io\/image\/fd-th\/Products\/3225880.jpg","item":"Ovaltine White Malt","price":"30"},{"cat":"Milk","dscr":"With choices of serving and topping available","icon":"https:\/\/raw.githubusercontent.com\/jalajoninc\/tha\/main\/chiang-mai\/nuch-coffee\/3225880.jpg","image":"https:\/\/images.deliveryhero.io\/image\/fd-th\/Products\/3225880.jpg","item":"Coconut Milk","price":"30"},{"cat":"Tea","dscr":"With choices of serving and topping available","icon":"https:\/\/raw.githubusercontent.com\/jalajoninc\/tha\/main\/chiang-mai\/nuch-coffee\/3225880.jpg","image":"https:\/\/images.deliveryhero.io\/image\/fd-th\/Products\/3225880.jpg","item":"Ice Milk Tea","price":"30"},{"cat":"Tea","dscr":"With choices of serving and topping available","icon":"https:\/\/raw.githubusercontent.com\/jalajoninc\/tha\/main\/chiang-mai\/nuch-coffee\/3225880.jpg","image":"https:\/\/images.deliveryhero.io\/image\/fd-th\/Products\/3225880.jpg","item":"Green Tea","price":"30"},{"cat":"Tea","dscr":"With choices of serving and topping available","icon":"https:\/\/raw.githubusercontent.com\/jalajoninc\/tha\/main\/chiang-mai\/nuch-coffee\/3225880.jpg","image":"https:\/\/images.deliveryhero.io\/image\/fd-th\/Products\/3225880.jpg","item":"Green Tea Milk","price":"30"},{"cat":"Tea","dscr":"With choices of serving and topping available","icon":"https:\/\/raw.githubusercontent.com\/jalajoninc\/tha\/main\/chiang-mai\/nuch-coffee\/3225880.jpg","image":"https:\/\/images.deliveryhero.io\/image\/fd-th\/Products\/3225880.jpg","item":"Lemon Tea","price":"30"},{"cat":"Tea","price":"30","item":"Lemon Green Tea","dscr":"With choices of serving and topping available"},{"cat":"Tea","price":"30","item":"Iced Nestea","dscr":"With choices of serving and topping available"},{"cat":"Juices","price":"30","item":"Orange","dscr":"With choices of serving and topping available"},{"cat":"Juices","price":"30","item":"Watermelon","dscr":"With choices of serving and topping available"},{"cat":"Juices","price":"30","item":"Lemon","dscr":"With choices of serving and topping available"},{"cat":"Juices","price":"30","item":"Banana","dscr":"With choices of serving and topping available"},{"cat":"Juices","price":"30","item":"Cantaloupe","dscr":"With choices of serving and topping available"},{"cat":"Juices","price":"30","item":"Taro","dscr":"With choices of serving and topping available"},{"cat":"Juices","price":"30","item":"Corn","dscr":"With choices of serving and topping available"}]