[{"cat":"Mains","icon":"https:\/\/raw.githubusercontent.com\/jalajoninc\/tha\/main\/kanchanaburi\/mod-dam-mod-dang-coconut\/10021770.jpg","price":"20","image":"https:\/\/images.deliveryhero.io\/image\/fd-th\/Products\/10021770.jpg","item":"Coconut"},{"cat":"Mains","dscr":"1 Kg","icon":"https:\/\/raw.githubusercontent.com\/jalajoninc\/tha\/main\/kanchanaburi\/mod-dam-mod-dang-coconut\/10021768.jpg","item":"Shredded Coconut Flakes","price":"70","image":"https:\/\/images.deliveryhero.io\/image\/fd-th\/Products\/10021768.jpg"},{"cat":"Mains","dscr":"1 Kg","icon":"https:\/\/raw.githubusercontent.com\/jalajoninc\/tha\/main\/kanchanaburi\/mod-dam-mod-dang-coconut\/10021768.jpg","item":"Coconut Milk","price":"75","image":"https:\/\/images.deliveryhero.io\/image\/fd-th\/Products\/10021768.jpg"},{"cat":"Mains","dscr":"1 Kg","icon":"https:\/\/raw.githubusercontent.com\/jalajoninc\/tha\/main\/kanchanaburi\/mod-dam-mod-dang-coconut\/10021771.jpg","item":"Grated Coconut Flakes","price":"80","image":"https:\/\/images.deliveryhero.io\/image\/fd-th\/Products\/10021771.jpg"},{"cat":"Mains","dscr":"1 Kg","icon":"https:\/\/raw.githubusercontent.com\/jalajoninc\/tha\/main\/kanchanaburi\/mod-dam-mod-dang-coconut\/10021767.jpg","item":"Mature Coconut","price":"70","image":"https:\/\/images.deliveryhero.io\/image\/fd-th\/Products\/10021767.jpg"},{"cat":"Mains","price":"30","item":"Coconut Sugar","dscr":"With choices of size available"}]