[{"cat":"A La Carte","dscr":"With choices of serving available","icon":"https:\/\/raw.githubusercontent.com\/jalajoninc\/tha\/main\/kanchanaburi\/rice-noodles-clay-pot-tonmakham\/9287117.jpg","image":"https:\/\/images.deliveryhero.io\/image\/fd-th\/Products\/9287117.jpg","item":"Rice Noodles with Curry Sauce","price":"45"},{"cat":"A La Carte","icon":"https:\/\/raw.githubusercontent.com\/jalajoninc\/tha\/main\/kanchanaburi\/rice-noodles-clay-pot-tonmakham\/9587697.jpg","price":"45","image":"https:\/\/images.deliveryhero.io\/image\/fd-th\/Products\/9587697.jpg","item":"Chicken Curry Vermicelli"},{"cat":"A La Carte","icon":"https:\/\/raw.githubusercontent.com\/jalajoninc\/tha\/main\/kanchanaburi\/rice-noodles-clay-pot-tonmakham\/9632200.jpg","price":"45","image":"https:\/\/images.deliveryhero.io\/image\/fd-th\/Products\/9632200.jpg","item":"Fish Stomach Curry Vermicelli"},{"cat":"A La Carte","icon":"https:\/\/raw.githubusercontent.com\/jalajoninc\/tha\/main\/kanchanaburi\/rice-noodles-clay-pot-tonmakham\/9632201.jpg","price":"45","image":"https:\/\/images.deliveryhero.io\/image\/fd-th\/Products\/9632201.jpg","item":"Fish Sauce Curry Vermicelli"},{"cat":"A La Carte","icon":"https:\/\/raw.githubusercontent.com\/jalajoninc\/tha\/main\/kanchanaburi\/rice-noodles-clay-pot-tonmakham\/9632202.jpg","price":"45","image":"https:\/\/images.deliveryhero.io\/image\/fd-th\/Products\/9632202.jpg","item":"Pork Curry Vermicelli"},{"price":"10","cat":"Sides","item":"Rice Noodles"},{"price":"10","cat":"Sides","item":"Cooked Rice"},{"price":"10","cat":"Sides","item":"Boiled Egg"}]