[{"cat":"Noodles Soup","price":"70","item":"Yentafo with Egg Noodles, Crispy Shrimp and Mixed Ingredients","dscr":"With choices of serving available"},{"cat":"Noodles Soup","price":"50","item":"Yentafo with Vegetables Soup, Crispy Shrimp and Mixed Ingredients","dscr":"With choices of serving available"},{"cat":"Noodles Soup","price":"50","item":"Yentafo with Crispy Shrimp and Mixed Ingredients","dscr":"With choices of serving and noodle available"},{"cat":"Noodles Soup","price":"50","item":"Yentafo with Shrimp Wonton, Crispy Shrimp and Mixed Ingredients","dscr":"With choices of serving available"},{"cat":"Noodles Soup","price":"50","item":"Noodles Soup with Meatball","dscr":"With choices of serving and noodle available"},{"cat":"Noodles Soup","price":"50","item":"Shrimp Wonton","dscr":"With choices of serving available"},{"cat":"Noodles Soup","price":"50","item":"Egg Nooldles with Shrimp Wonton","dscr":"With choices of serving available"}]