[{"cat":"Desserts","icon":"https:\/\/raw.githubusercontent.com\/jalajoninc\/tha\/main\/lamphun\/a-cocoa-bang\/9920438.jpg","price":"20","image":"https:\/\/images.deliveryhero.io\/image\/fd-th\/Products\/9920438.jpg","item":"Thai Tea Custard Bun"},{"cat":"Desserts","icon":"https:\/\/raw.githubusercontent.com\/jalajoninc\/tha\/main\/lamphun\/a-cocoa-bang\/9920439.jpg","price":"20","image":"https:\/\/images.deliveryhero.io\/image\/fd-th\/Products\/9920439.jpg","item":"Chili Paste and Crabstick Bun"},{"cat":"Desserts","icon":"https:\/\/raw.githubusercontent.com\/jalajoninc\/tha\/main\/lamphun\/a-cocoa-bang\/9920433.jpg","price":"20","image":"https:\/\/images.deliveryhero.io\/image\/fd-th\/Products\/9920433.jpg","item":"Milk and Milo Powder Bun"},{"cat":"Desserts","icon":"https:\/\/raw.githubusercontent.com\/jalajoninc\/tha\/main\/lamphun\/a-cocoa-bang\/9920433.jpg","price":"20","image":"https:\/\/images.deliveryhero.io\/image\/fd-th\/Products\/9920433.jpg","item":"Chocolate Bun"},{"cat":"Desserts","icon":"https:\/\/raw.githubusercontent.com\/jalajoninc\/tha\/main\/lamphun\/a-cocoa-bang\/9920432.jpg","price":"20","image":"https:\/\/images.deliveryhero.io\/image\/fd-th\/Products\/9920432.jpg","item":"Pandan Custard Bun"},{"cat":"Desserts","icon":"https:\/\/raw.githubusercontent.com\/jalajoninc\/tha\/main\/lamphun\/a-cocoa-bang\/9920435.jpg","price":"20","image":"https:\/\/images.deliveryhero.io\/image\/fd-th\/Products\/9920435.jpg","item":"Milk Cream Bun"},{"cat":"Desserts","icon":"https:\/\/raw.githubusercontent.com\/jalajoninc\/tha\/main\/lamphun\/a-cocoa-bang\/9920434.jpg","price":"20","image":"https:\/\/images.deliveryhero.io\/image\/fd-th\/Products\/9920434.jpg","item":"Chili Paste and Pork Floss Bun"},{"cat":"Desserts","icon":"https:\/\/raw.githubusercontent.com\/jalajoninc\/tha\/main\/lamphun\/a-cocoa-bang\/9920436.jpg","price":"20","image":"https:\/\/images.deliveryhero.io\/image\/fd-th\/Products\/9920436.jpg","item":"Coconut Cream Bun"},{"cat":"Desserts","icon":"https:\/\/raw.githubusercontent.com\/jalajoninc\/tha\/main\/lamphun\/a-cocoa-bang\/9920428.jpg","price":"20","image":"https:\/\/images.deliveryhero.io\/image\/fd-th\/Products\/9920428.jpg","item":"Strawberry Jam Bun"},{"cat":"Desserts","icon":"https:\/\/raw.githubusercontent.com\/jalajoninc\/tha\/main\/lamphun\/a-cocoa-bang\/9920428.jpg","price":"20","image":"https:\/\/images.deliveryhero.io\/image\/fd-th\/Products\/9920428.jpg","item":"Blueberry Jam Bun"},{"cat":"Beverages","dscr":"Milk and cocoa 50%. With choices of toppings available","icon":"https:\/\/raw.githubusercontent.com\/jalajoninc\/tha\/main\/lamphun\/a-cocoa-bang\/9920428.jpg","item":"Yummy Beginning","price":"35","image":"https:\/\/images.deliveryhero.io\/image\/fd-th\/Products\/9920428.jpg"},{"cat":"Beverages","dscr":"Milk 10% and cocoa 90%. With choices of toppings available","icon":"https:\/\/raw.githubusercontent.com\/jalajoninc\/tha\/main\/lamphun\/a-cocoa-bang\/9920430.jpg","item":"Say Before that Dark or Light","price":"40","image":"https:\/\/images.deliveryhero.io\/image\/fd-th\/Products\/9920430.jpg"},{"cat":"Beverages","dscr":"Milk 20% , banana 30%, and cocoa 50%. With choices of toppings available","icon":"https:\/\/raw.githubusercontent.com\/jalajoninc\/tha\/main\/lamphun\/a-cocoa-bang\/9920431.jpg","item":"Full Delicious","price":"40","image":"https:\/\/images.deliveryhero.io\/image\/fd-th\/Products\/9920431.jpg"},{"cat":"Beverages","dscr":"Milk 10% , mint 20%, and cocoa 90%. With choices of toppings available","icon":"https:\/\/raw.githubusercontent.com\/jalajoninc\/tha\/main\/lamphun\/a-cocoa-bang\/9920431.jpg","item":"Sweet Cool and Dark","price":"35","image":"https:\/\/images.deliveryhero.io\/image\/fd-th\/Products\/9920431.jpg"}]