[{"cat":"Beverage","dscr":"สามารถเลือกรูปแบบและท็อปปิ้งได้","icon":"https:\/\/raw.githubusercontent.com\/jalajoninc\/tha\/main\/lamphun\/ban-tong-coffee-bakery\/2136082.jpg","item":"อเมริกาโน่","price":"30","image":"https:\/\/images.deliveryhero.io\/image\/fd-th\/Products\/2136082.jpg"},{"cat":"Beverage","dscr":"สามารถเลือกรูปแบบและท็อปปิ้งได้","icon":"https:\/\/raw.githubusercontent.com\/jalajoninc\/tha\/main\/lamphun\/ban-tong-coffee-bakery\/2136083.jpg","item":"เอสเพรสโซ่","price":"30","image":"https:\/\/images.deliveryhero.io\/image\/fd-th\/Products\/2136083.jpg"},{"cat":"Beverage","dscr":"สามารถเลือกรูปแบบและท็อปปิ้งได้","icon":"https:\/\/raw.githubusercontent.com\/jalajoninc\/tha\/main\/lamphun\/ban-tong-coffee-bakery\/2136084.jpg","item":"คาราเมลมัคคิอาโต้","price":"45","image":"https:\/\/images.deliveryhero.io\/image\/fd-th\/Products\/2136084.jpg"},{"cat":"Beverage","dscr":"สามารถเลือกรูปแบบและท็อปปิ้งได้","icon":"https:\/\/raw.githubusercontent.com\/jalajoninc\/tha\/main\/lamphun\/ban-tong-coffee-bakery\/2136085.jpg","item":"คาปูชิโน่","price":"30","image":"https:\/\/images.deliveryhero.io\/image\/fd-th\/Products\/2136085.jpg"},{"cat":"Beverage","dscr":"สามารถเลือกรูปแบบและท็อปปิ้งได้","icon":"https:\/\/raw.githubusercontent.com\/jalajoninc\/tha\/main\/lamphun\/ban-tong-coffee-bakery\/2136086.jpg","item":"มอคค่า","price":"30","image":"https:\/\/images.deliveryhero.io\/image\/fd-th\/Products\/2136086.jpg"},{"cat":"Beverage","dscr":"สามารถเลือกรูปแบบและท็อปปิ้งได้","icon":"https:\/\/raw.githubusercontent.com\/jalajoninc\/tha\/main\/lamphun\/ban-tong-coffee-bakery\/2136087.jpg","item":"ลาเต้","price":"30","image":"https:\/\/images.deliveryhero.io\/image\/fd-th\/Products\/2136087.jpg"},{"cat":"Beverage","dscr":"สามารถเลือกท็อปปิ้งได้","icon":"https:\/\/raw.githubusercontent.com\/jalajoninc\/tha\/main\/lamphun\/ban-tong-coffee-bakery\/2136088.jpg","item":"กาแฟบ้านตอง","price":"45","image":"https:\/\/images.deliveryhero.io\/image\/fd-th\/Products\/2136088.jpg"},{"cat":"Beverage","dscr":"สามารถเลือกรูปแบบและท็อปปิ้งได้","icon":"https:\/\/raw.githubusercontent.com\/jalajoninc\/tha\/main\/lamphun\/ban-tong-coffee-bakery\/2136089.jpg","item":"ชาเขียว","price":"30","image":"https:\/\/images.deliveryhero.io\/image\/fd-th\/Products\/2136089.jpg"},{"cat":"Beverage","dscr":"สามารถเลือกรูปแบบและท็อปปิ้งได้","icon":"https:\/\/raw.githubusercontent.com\/jalajoninc\/tha\/main\/lamphun\/ban-tong-coffee-bakery\/2136090.jpg","item":"ชาเขียวมัทฉะ","price":"45","image":"https:\/\/images.deliveryhero.io\/image\/fd-th\/Products\/2136090.jpg"},{"cat":"Beverage","dscr":"สามารถเลือกรูปแบบและท็อปปิ้งได้","icon":"https:\/\/raw.githubusercontent.com\/jalajoninc\/tha\/main\/lamphun\/ban-tong-coffee-bakery\/2136091.jpg","item":"ชาพีช","price":"30","image":"https:\/\/images.deliveryhero.io\/image\/fd-th\/Products\/2136091.jpg"},{"cat":"Beverage","dscr":"สามารถเลือกรูปแบบและท็อปปิ้งได้","icon":"https:\/\/raw.githubusercontent.com\/jalajoninc\/tha\/main\/lamphun\/ban-tong-coffee-bakery\/2136092.jpg","item":"ชาเย็น","price":"30","image":"https:\/\/images.deliveryhero.io\/image\/fd-th\/Products\/2136092.jpg"},{"cat":"Beverage","dscr":"สามารถเลือกท็อปปิ้งได้","icon":"https:\/\/raw.githubusercontent.com\/jalajoninc\/tha\/main\/lamphun\/ban-tong-coffee-bakery\/2136093.jpg","item":"ชามะนาว","price":"30","image":"https:\/\/images.deliveryhero.io\/image\/fd-th\/Products\/2136093.jpg"},{"cat":"Beverage","dscr":"สามารถเลือกท็อปปิ้งได้","icon":"https:\/\/raw.githubusercontent.com\/jalajoninc\/tha\/main\/lamphun\/ban-tong-coffee-bakery\/6127954.jpg","item":"มอคค่าโอริโอ้ ปั่น","price":"45","image":"https:\/\/images.deliveryhero.io\/image\/fd-th\/Products\/6127954.jpg"},{"dscr":"สามารถเลือกรูปแบบและท็อปปิ้งได้","icon":"https:\/\/raw.githubusercontent.com\/jalajoninc\/tha\/main\/lamphun\/ban-tong-coffee-bakery\/2136094.jpg","item":"โกโก้","price":"30","image":"https:\/\/images.deliveryhero.io\/image\/fd-th\/Products\/2136094.jpg"},{"dscr":"สามารถเลือกรูปแบบและท็อปปิ้งได้","icon":"https:\/\/raw.githubusercontent.com\/jalajoninc\/tha\/main\/lamphun\/ban-tong-coffee-bakery\/2136095.jpg","item":"นมมิ้นท์","price":"30","image":"https:\/\/images.deliveryhero.io\/image\/fd-th\/Products\/2136095.jpg"},{"dscr":"สามารถเลือกรูปแบบและท็อปปิ้งได้","icon":"https:\/\/raw.githubusercontent.com\/jalajoninc\/tha\/main\/lamphun\/ban-tong-coffee-bakery\/2136096.jpg","item":"นมคาราเมล","price":"35","image":"https:\/\/images.deliveryhero.io\/image\/fd-th\/Products\/2136096.jpg"},{"dscr":"สามารถเลือกรูปแบบและท็อปปิ้งได้","icon":"https:\/\/raw.githubusercontent.com\/jalajoninc\/tha\/main\/lamphun\/ban-tong-coffee-bakery\/6127940.jpg","item":"ช็อกโกแลตมิ้นท์","price":"40","image":"https:\/\/images.deliveryhero.io\/image\/fd-th\/Products\/6127940.jpg"},{"dscr":"สามารถเลือกรูปแบบและท็อปปิ้งได้","icon":"https:\/\/raw.githubusercontent.com\/jalajoninc\/tha\/main\/lamphun\/ban-tong-coffee-bakery\/6127940.jpg","item":"นมสดบราวชูการ์","price":"35","image":"https:\/\/images.deliveryhero.io\/image\/fd-th\/Products\/6127940.jpg"},{"dscr":"Milkoreo","icon":"https:\/\/raw.githubusercontent.com\/jalajoninc\/tha\/main\/lamphun\/ban-tong-coffee-bakery\/6284607.jpg","item":"Oreo","price":"40","image":"https:\/\/images.deliveryhero.io\/image\/fd-th\/Products\/6284607.jpg"},{"dscr":"สามารถเลือกรูปแบบและท็อปปิ้งได้","icon":"https:\/\/raw.githubusercontent.com\/jalajoninc\/tha\/main\/lamphun\/ban-tong-coffee-bakery\/2136098.jpg","item":"กีวี่","price":"25","image":"https:\/\/images.deliveryhero.io\/image\/fd-th\/Products\/2136098.jpg"},{"dscr":"สามารถเลือกรูปแบบและท็อปปิ้งได้","icon":"https:\/\/raw.githubusercontent.com\/jalajoninc\/tha\/main\/lamphun\/ban-tong-coffee-bakery\/2136100.jpg","item":"แคนตาลูป","price":"25","image":"https:\/\/images.deliveryhero.io\/image\/fd-th\/Products\/2136100.jpg"},{"dscr":"สามารถเลือกรูปแบบและท็อปปิ้งได้","icon":"https:\/\/raw.githubusercontent.com\/jalajoninc\/tha\/main\/lamphun\/ban-tong-coffee-bakery\/2136102.jpg","item":"เสาวรส","price":"25","image":"https:\/\/images.deliveryhero.io\/image\/fd-th\/Products\/2136102.jpg"},{"icon":"https:\/\/raw.githubusercontent.com\/jalajoninc\/tha\/main\/lamphun\/ban-tong-coffee-bakery\/10572193.jpg","price":"35","image":"https:\/\/images.deliveryhero.io\/image\/fd-th\/Products\/10572193.jpg","item":"Butterfly Pea Milk Tea"},{"icon":"https:\/\/raw.githubusercontent.com\/jalajoninc\/tha\/main\/lamphun\/ban-tong-coffee-bakery\/10572195.jpg","price":"45","image":"https:\/\/images.deliveryhero.io\/image\/fd-th\/Products\/10572195.jpg","item":"Butterfly Pea Latte"}]