[{"cat":"Noodles","price":"50","item":"Pork Noodles Soup","dscr":"With choices of serving, meat, noodles and soup available"},{"cat":"Noodles","price":"60","item":"Beef Noodles Soup","dscr":"With choices of serving, meat, noodles and soup available"},{"cat":"Noodles","price":"70","item":"Pork Soup","dscr":"With choices of serving, meat and soup available"},{"cat":"Noodles","price":"70","item":"Beef Soup","dscr":"With choices of serving, meat and soup available"},{"cat":"Noodles","price":"60","item":"Yentafo Noodles Soup","dscr":"With choices of serving, noodles and soup available"},{"cat":"Noodles","price":"60","item":"Fish Noodles Soup","dscr":"With choices of serving, noodles and soup available"},{"cat":"Noodles","price":"80","item":"Seafood Yentafo Noodles Soup","dscr":"Shrimp, squid and fish balls, with choices of serving, noodles and soup available"},{"cat":"Noodles","price":"80","item":"Yentafo Soup","dscr":"สามารถเลือกรูปแบบได้"}]