[{"price":"50","cat":"Appetizers","item":"Boiled Beef Meatballs"},{"price":"50","cat":"Appetizers","item":"Boiled Pork Meatballs"},{"price":"50","cat":"Appetizers","item":"Boiled Vietnamese Pork Sausage"},{"price":"60","cat":"Appetizers","item":"Boiled Mixed Beef"},{"cat":"Mains","price":"50","item":"Beef Noodles","dscr":"With choices of noodle, meat and serving available"},{"cat":"Mains","price":"50","item":"Pork Noodles","dscr":"With choices of noodle, meat and serving available"},{"cat":"Mains","price":"50","item":"Tom Yum Thicken Soup Noodles with Egg","dscr":"With choices of noodle available"},{"cat":"Mains","price":"50","item":"Beef Soup","dscr":"With choices of serving and meat available"},{"cat":"Mains","price":"50","item":"Pork Soup","dscr":"With choices of serving and meat available"},{"cat":"Mains","price":"50","item":"Egg Noodles","dscr":"With choices of serving and meat available"},{"cat":"Mains","price":"50","item":"Egg Noodles with Dumplings","dscr":"With choices of meat available"},{"cat":"Mains","price":"50","item":"Vietnamese Rice Noodle Soup","dscr":"With vietnamese pork sausage, egg and pork jerky"},{"price":"10","cat":"Sides","item":"Pork Jerky"},{"price":"10","cat":"Sides","item":"Egg"},{"price":"10","cat":"Sides","item":"Steamed Rice"}]