[{"cat":"Sets","icon":"https:\/\/images.deliveryhero.io\/image\/fd-th\/Products\/7326834.jpg","item":"Grilled Pork with Fermented Fish Set","price":"119","dscr":"Served with fermented fish chili dip, cucumber and cabbage. With choices of size available"},{"cat":"Sets","icon":"https:\/\/images.deliveryhero.io\/image\/fd-th\/Products\/7326835.jpg","item":"Grilled Beef with Fermented Fish Set","price":"129","dscr":"Served with fermented fish chili dip, cucumber and cabbage. With choices of size available"},{"cat":"Mains","price":"25","item":"Grilled Beef with Fermented Fish"},{"cat":"Mains","price":"20","item":"Grilled Pork with Fermented Fish"},{"cat":"Sides","price":"10","item":"Sticky Rice"},{"cat":"Sides","price":"20","item":"Fresh Vegetable Set","dscr":"Cucumber and cabbage"}]