[{"price":"50","dscr":"สามารถเลือกน้ำซุป เส้น และท็อปปิ้งได้","item":"ก๋วยเตี๋ยวลูกชิ้นเนื้อ"},{"price":"50","dscr":"สามารถเลือกน้ำซุป เส้น และท็อปปิ้งได้","item":"ก๋วยเตี๋ยวลูกชิ้นเอ็นเนื้อ"},{"price":"50","dscr":"สามารถเลือกน้ำซุป เส้น และท็อปปิ้งได้","item":"ก๋วยเตี๋ยวเนื้อสด"},{"price":"50","dscr":"สามารถเลือกน้ำซุป เส้น และท็อปปิ้งได้","item":"ก๋วยเตี๋ยวเนื้อเปื่อย"},{"price":"50","dscr":"สามารถเลือกน้ำซุป เส้น และท็อปปิ้งได้","item":"ก๋วยเตี๋ยวลูกชิ้นเนื้อ เนื้อสด"},{"price":"50","dscr":"สามารถเลือกน้ำซุป เส้น และท็อปปิ้งได้","item":"ก๋วยเตี๋ยวลูกชิ้นเนื้อ เนื้อเปื่อย"},{"price":"60","dscr":"สามารถเลือกน้ำซุป เส้น และท็อปปิ้งได้","item":"ก๋วยเตี๋ยวลูกชิ้นเนื้อ เนื้อสด ตีนไก่"},{"price":"60","dscr":"สามารถเลือกน้ำซุป เส้น และท็อปปิ้งได้","item":"ก๋วยเตี๋ยวลูกชิ้นเนื้อ เนื้อเปื่อย ตีนไก่"},{"price":"60","dscr":"สามารถเลือกน้ำซุป เส้น และท็อปปิ้งได้","item":"ก๋วยเตี๋ยวลูกชิ้นเนื้อ เนื้อสด เนื้อเปื่อย"},{"price":"60","dscr":"สามารถเลือกน้ำซุป เส้น และท็อปปิ้งได้","item":"ก๋วยเตี๋ยวน่องไก่ ลูกชิ้นเนื้อ  เนื้อเปื่อย"},{"price":"60","dscr":"สามารถเลือกน้ำซุป เส้น และท็อปปิ้งได้","item":"ก๋วยเตี๋ยวน่องไก่ ลูกชิ้นเนื้อ เนื้อสด"},{"price":"60","dscr":"สามารถเลือกน้ำซุป เส้น และท็อปปิ้งได้","item":"ก๋วยเตี๋ยวน่องไก่ ลูกชิ้นเนื้อ"},{"price":"70","dscr":"สามารถเลือกน้ำซุป เส้น และท็อปปิ้งได้","item":"ก๋วยเตี๋ยวรวมเนื้อ น่องไก่ ตีนไก่"},{"price":"45","dscr":"สามารถเลือกน้ำซุป เส้น และท็อปปิ้งได้","item":"ก๋วยเตี๋ยวลูกชิ้นปลา"},{"price":"50","dscr":"สามารถเลือกน้ำซุป เส้น และท็อปปิ้งได้","item":"ก๋วยเตี๋ยวน่องไก่"},{"price":"50","dscr":"สามารถเลือกน้ำซุป เส้น และท็อปปิ้งได้","item":"ก๋วยเตี๋ยวตีนไก่"},{"price":"50","dscr":"สามารถเลือกน้ำซุป เส้น และท็อปปิ้งได้","item":"ก๋วยเตี๋ยวทะเล"},{"price":"70","dscr":"สามารถเลือกน้ำซุป เส้น และท็อปปิ้งได้","item":"ก๋วยเตี๋ยวทะเล น่องไก่"},{"price":"60","dscr":"สามารถเลือกน้ำซุป เส้น และท็อปปิ้งได้","item":"ก๋วยเตี๋ยวน่องไก่ ลูกชิ้นปลา"},{"price":"60","dscr":"สามารถเลือกน้ำซุป เส้น และท็อปปิ้งได้","item":"ก๋วยเตี๋ยวน่องไก่ ตีนไก่"},{"price":"45","dscr":"สามารถเลือกเส้น และท็อปปิ้งได้","item":"ก๋วยเตี๋ยวเย็นตาโฟ"},{"price":"70","dscr":"สามารถเลือกเส้น และท็อปปิ้งได้","item":"ก๋วยเตี๋ยวเย็นตาโฟ น่องไก่"},{"price":"40","dscr":"สามารถเลือกเส้น และท็อปปิ้งได้","item":"ก๋วยเตี๋ยวต้มยำลูกชิ้นปลา ปลาแผ่น"}]