[{"cat":"A La Carte","price":"45","item":"Stir Fried Basil with Rice","dscr":"With choices of meat and spiciness level available"},{"cat":"A La Carte","price":"45","item":"Stir Fried Roasted Chili Paste with Rice","dscr":"With choices of meat and spiciness level available"},{"cat":"A La Carte","price":"45","item":"Stir Fried Curry Paste with Rice","dscr":"With choices of meat and spiciness level available"},{"cat":"A La Carte","price":"45","item":"Stir Fried Curry Paste and Bamboo Shoot with Rice","dscr":"With choices of meat and spiciness level available"},{"cat":"A La Carte","price":"45","item":"Stir Fried Bell Pepper with Rice","dscr":"With choices of meat and spiciness level available"},{"cat":"A La Carte","price":"45","item":"Fried Rice with Egg","dscr":"With choices of meat available"},{"cat":"A La Carte","price":"40","item":"Rice Porridge","dscr":"With choices of meat available"},{"cat":"Mains","price":"95","item":"Tom Yum Soup","dscr":"With choices of meat, serving and spiciness level available"},{"price":"65","cat":"Mains","item":"Stir Fried Chinese Kale and Crispy Pork Belly"},{"cat":"Mains","price":"65","item":"Stir Fried Preserved Egg and Basil","dscr":"With choices of spiciness level available"},{"cat":"Mains","price":"65","item":"Spicy Stir Fried","dscr":"With choices of meat and spiciness level available"}]