[{"cat":"Iced Coffee","dscr":"Signature coffee","icon":"https:\/\/raw.githubusercontent.com\/jalajoninc\/tha\/main\/chanthaburi\/coffee-today-1\/10593710.jpg","image":"https:\/\/images.deliveryhero.io\/image\/fd-th\/Products\/10593710.jpg","item":"Today Iced Coffee","price":"50"},{"cat":"Iced Coffee","icon":"https:\/\/raw.githubusercontent.com\/jalajoninc\/tha\/main\/chanthaburi\/coffee-today-1\/10593712.jpg","price":"55","image":"https:\/\/images.deliveryhero.io\/image\/fd-th\/Products\/10593712.jpg","item":"Iced Cappuccino"},{"cat":"Iced Coffee","icon":"https:\/\/raw.githubusercontent.com\/jalajoninc\/tha\/main\/chanthaburi\/coffee-today-1\/10593711.jpg","price":"50","image":"https:\/\/images.deliveryhero.io\/image\/fd-th\/Products\/10593711.jpg","item":"Iced Espresso"},{"cat":"Iced Coffee","icon":"https:\/\/raw.githubusercontent.com\/jalajoninc\/tha\/main\/chanthaburi\/coffee-today-1\/10593717.jpg","price":"55","image":"https:\/\/images.deliveryhero.io\/image\/fd-th\/Products\/10593717.jpg","item":"Iced Mocha"},{"cat":"Iced Coffee","icon":"https:\/\/raw.githubusercontent.com\/jalajoninc\/tha\/main\/chanthaburi\/coffee-today-1\/10593718.jpg","price":"55","image":"https:\/\/images.deliveryhero.io\/image\/fd-th\/Products\/10593718.jpg","item":"Iced Latte"},{"cat":"Iced Coffee","icon":"https:\/\/raw.githubusercontent.com\/jalajoninc\/tha\/main\/chanthaburi\/coffee-today-1\/10593716.jpg","price":"50","image":"https:\/\/images.deliveryhero.io\/image\/fd-th\/Products\/10593716.jpg","item":"Iced Espuccino"},{"cat":"Iced Coffee","icon":"https:\/\/raw.githubusercontent.com\/jalajoninc\/tha\/main\/chanthaburi\/coffee-today-1\/10593713.jpg","price":"50","image":"https:\/\/images.deliveryhero.io\/image\/fd-th\/Products\/10593713.jpg","item":"Iced Americano"},{"cat":"Iced Coffee","icon":"https:\/\/raw.githubusercontent.com\/jalajoninc\/tha\/main\/chanthaburi\/coffee-today-1\/10593715.jpg","price":"60","image":"https:\/\/images.deliveryhero.io\/image\/fd-th\/Products\/10593715.jpg","item":"Iced Caramel Macchiato"},{"cat":"Iced Coffee","icon":"https:\/\/raw.githubusercontent.com\/jalajoninc\/tha\/main\/chanthaburi\/coffee-today-1\/10593714.jpg","price":"60","image":"https:\/\/images.deliveryhero.io\/image\/fd-th\/Products\/10593714.jpg","item":"Iced Americano with Honey"},{"cat":"Coffee Frappe","icon":"https:\/\/raw.githubusercontent.com\/jalajoninc\/tha\/main\/chanthaburi\/coffee-today-1\/10593719.jpg","price":"55","image":"https:\/\/images.deliveryhero.io\/image\/fd-th\/Products\/10593719.jpg","item":"Espresso Frappe"},{"cat":"Coffee Frappe","icon":"https:\/\/raw.githubusercontent.com\/jalajoninc\/tha\/main\/chanthaburi\/coffee-today-1\/10593723.jpg","price":"60","image":"https:\/\/images.deliveryhero.io\/image\/fd-th\/Products\/10593723.jpg","item":"Cappuccino Frappe"},{"cat":"Coffee Frappe","icon":"https:\/\/raw.githubusercontent.com\/jalajoninc\/tha\/main\/chanthaburi\/coffee-today-1\/10593721.jpg","price":"60","image":"https:\/\/images.deliveryhero.io\/image\/fd-th\/Products\/10593721.jpg","item":"Mocha Frappe"},{"cat":"Coffee Frappe","icon":"https:\/\/raw.githubusercontent.com\/jalajoninc\/tha\/main\/chanthaburi\/coffee-today-1\/10593720.jpg","price":"55","image":"https:\/\/images.deliveryhero.io\/image\/fd-th\/Products\/10593720.jpg","item":"Today Coffee Frappe"},{"cat":"Coffee Frappe","icon":"https:\/\/raw.githubusercontent.com\/jalajoninc\/tha\/main\/chanthaburi\/coffee-today-1\/10593722.jpg","price":"55","image":"https:\/\/images.deliveryhero.io\/image\/fd-th\/Products\/10593722.jpg","item":"Espuccino Frappe"},{"cat":"Coffee Frappe","icon":"https:\/\/raw.githubusercontent.com\/jalajoninc\/tha\/main\/chanthaburi\/coffee-today-1\/10593724.jpg","price":"65","image":"https:\/\/images.deliveryhero.io\/image\/fd-th\/Products\/10593724.jpg","item":"Caramel Macchiato Frappe"},{"cat":"Iced Tea","icon":"https:\/\/raw.githubusercontent.com\/jalajoninc\/tha\/main\/chanthaburi\/coffee-today-1\/10593726.jpg","price":"45","image":"https:\/\/images.deliveryhero.io\/image\/fd-th\/Products\/10593726.jpg","item":"Iced Lemon Tea"},{"cat":"Iced Tea","icon":"https:\/\/raw.githubusercontent.com\/jalajoninc\/tha\/main\/chanthaburi\/coffee-today-1\/10593739.jpg","price":"40","image":"https:\/\/images.deliveryhero.io\/image\/fd-th\/Products\/10593739.jpg","item":"Iced Green Tea"},{"cat":"Iced Tea","icon":"https:\/\/raw.githubusercontent.com\/jalajoninc\/tha\/main\/chanthaburi\/coffee-today-1\/10593739.jpg","price":"45","image":"https:\/\/images.deliveryhero.io\/image\/fd-th\/Products\/10593739.jpg","item":"Iced Apple Tea"},{"cat":"Iced Tea","icon":"https:\/\/raw.githubusercontent.com\/jalajoninc\/tha\/main\/chanthaburi\/coffee-today-1\/10593736.jpg","price":"45","image":"https:\/\/images.deliveryhero.io\/image\/fd-th\/Products\/10593736.jpg","item":"Iced Green Tea with Milk"},{"cat":"Iced Tea","icon":"https:\/\/raw.githubusercontent.com\/jalajoninc\/tha\/main\/chanthaburi\/coffee-today-1\/10593727.jpg","price":"45","image":"https:\/\/images.deliveryhero.io\/image\/fd-th\/Products\/10593727.jpg","item":"Iced Thai Tea"},{"cat":"Iced Tea","icon":"https:\/\/raw.githubusercontent.com\/jalajoninc\/tha\/main\/chanthaburi\/coffee-today-1\/10593737.jpg","price":"45","image":"https:\/\/images.deliveryhero.io\/image\/fd-th\/Products\/10593737.jpg","item":"Iced Peach Tea"},{"cat":"Iced Tea","icon":"https:\/\/raw.githubusercontent.com\/jalajoninc\/tha\/main\/chanthaburi\/coffee-today-1\/10593732.jpg","price":"45","image":"https:\/\/images.deliveryhero.io\/image\/fd-th\/Products\/10593732.jpg","item":"Iced Thai Black Tea"},{"cat":"Iced Tea","icon":"https:\/\/raw.githubusercontent.com\/jalajoninc\/tha\/main\/chanthaburi\/coffee-today-1\/10593732.jpg","price":"65","image":"https:\/\/images.deliveryhero.io\/image\/fd-th\/Products\/10593732.jpg","item":"Iced Matcha Green Tea"},{"cat":"Iced Tea","icon":"https:\/\/raw.githubusercontent.com\/jalajoninc\/tha\/main\/chanthaburi\/coffee-today-1\/10593729.jpg","price":"60","image":"https:\/\/images.deliveryhero.io\/image\/fd-th\/Products\/10593729.jpg","item":"Iced Honey and Lemon Tea"},{"cat":"Iced Tea","icon":"https:\/\/raw.githubusercontent.com\/jalajoninc\/tha\/main\/chanthaburi\/coffee-today-1\/10593742.jpg","price":"55","image":"https:\/\/images.deliveryhero.io\/image\/fd-th\/Products\/10593742.jpg","item":"Iced Twinings Earl Grey Tea"},{"cat":"Iced Tea","icon":"https:\/\/raw.githubusercontent.com\/jalajoninc\/tha\/main\/chanthaburi\/coffee-today-1\/10593742.jpg","price":"55","image":"https:\/\/images.deliveryhero.io\/image\/fd-th\/Products\/10593742.jpg","item":"Iced Twinings English Breakfast Tea"},{"cat":"Iced Tea","icon":"https:\/\/raw.githubusercontent.com\/jalajoninc\/tha\/main\/chanthaburi\/coffee-today-1\/10593742.jpg","price":"55","image":"https:\/\/images.deliveryhero.io\/image\/fd-th\/Products\/10593742.jpg","item":"Iced Twinings Chamomile Tea"},{"cat":"Iced Tea","icon":"https:\/\/raw.githubusercontent.com\/jalajoninc\/tha\/main\/chanthaburi\/coffee-today-1\/10593742.jpg","price":"55","image":"https:\/\/images.deliveryhero.io\/image\/fd-th\/Products\/10593742.jpg","item":"Iced Twinings Peppermint Tea"},{"cat":"Iced Tea","icon":"https:\/\/raw.githubusercontent.com\/jalajoninc\/tha\/main\/chanthaburi\/coffee-today-1\/10593742.jpg","price":"55","image":"https:\/\/images.deliveryhero.io\/image\/fd-th\/Products\/10593742.jpg","item":"Iced Twinings Vanilla Tea"},{"cat":"Iced Tea","icon":"https:\/\/raw.githubusercontent.com\/jalajoninc\/tha\/main\/chanthaburi\/coffee-today-1\/10593742.jpg","price":"55","image":"https:\/\/images.deliveryhero.io\/image\/fd-th\/Products\/10593742.jpg","item":"Iced Twinings Four Red Fruits Tea"},{"cat":"Iced Tea","icon":"https:\/\/raw.githubusercontent.com\/jalajoninc\/tha\/main\/chanthaburi\/coffee-today-1\/10593742.jpg","price":"55","image":"https:\/\/images.deliveryhero.io\/image\/fd-th\/Products\/10593742.jpg","item":"Iced Twinings Strawberry and Mango Tea"},{"cat":"Tea Frappe","icon":"https:\/\/raw.githubusercontent.com\/jalajoninc\/tha\/main\/chanthaburi\/coffee-today-1\/10593742.jpg","price":"50","image":"https:\/\/images.deliveryhero.io\/image\/fd-th\/Products\/10593742.jpg","item":"Peach Tea Frappe"},{"cat":"Tea Frappe","icon":"https:\/\/raw.githubusercontent.com\/jalajoninc\/tha\/main\/chanthaburi\/coffee-today-1\/10593741.jpg","price":"50","image":"https:\/\/images.deliveryhero.io\/image\/fd-th\/Products\/10593741.jpg","item":"Thai Tea Frappe"},{"cat":"Tea Frappe","icon":"https:\/\/raw.githubusercontent.com\/jalajoninc\/tha\/main\/chanthaburi\/coffee-today-1\/10593744.jpg","price":"50","image":"https:\/\/images.deliveryhero.io\/image\/fd-th\/Products\/10593744.jpg","item":"Green Tea with Milk Frappe"},{"cat":"Tea Frappe","icon":"https:\/\/raw.githubusercontent.com\/jalajoninc\/tha\/main\/chanthaburi\/coffee-today-1\/10593745.jpg","price":"50","image":"https:\/\/images.deliveryhero.io\/image\/fd-th\/Products\/10593745.jpg","item":"Apple Tea Frappe"},{"cat":"Tea Frappe","icon":"https:\/\/raw.githubusercontent.com\/jalajoninc\/tha\/main\/chanthaburi\/coffee-today-1\/10593743.jpg","price":"50","image":"https:\/\/images.deliveryhero.io\/image\/fd-th\/Products\/10593743.jpg","item":"Lemon Tea Frappe"},{"cat":"Iced Milk","icon":"https:\/\/raw.githubusercontent.com\/jalajoninc\/tha\/main\/chanthaburi\/coffee-today-1\/10593750.jpg","price":"45","image":"https:\/\/images.deliveryhero.io\/image\/fd-th\/Products\/10593750.jpg","item":"Iced Chocolate"},{"cat":"Iced Milk","icon":"https:\/\/raw.githubusercontent.com\/jalajoninc\/tha\/main\/chanthaburi\/coffee-today-1\/10593746.jpg","price":"65","image":"https:\/\/images.deliveryhero.io\/image\/fd-th\/Products\/10593746.jpg","item":"Iced Brown Sugar Fresh Milk"},{"cat":"Iced Milk","icon":"https:\/\/raw.githubusercontent.com\/jalajoninc\/tha\/main\/chanthaburi\/coffee-today-1\/10593748.jpg","price":"55","image":"https:\/\/images.deliveryhero.io\/image\/fd-th\/Products\/10593748.jpg","item":"Iced Caramel Fresh Milk"},{"cat":"Iced Milk","icon":"https:\/\/raw.githubusercontent.com\/jalajoninc\/tha\/main\/chanthaburi\/coffee-today-1\/10593747.jpg","price":"45","image":"https:\/\/images.deliveryhero.io\/image\/fd-th\/Products\/10593747.jpg","item":"Iced Cocoa"},{"cat":"Iced Milk","icon":"https:\/\/raw.githubusercontent.com\/jalajoninc\/tha\/main\/chanthaburi\/coffee-today-1\/10593749.jpg","price":"45","image":"https:\/\/images.deliveryhero.io\/image\/fd-th\/Products\/10593749.jpg","item":"Iced Fresh Milk"},{"cat":"Milk Frappe","icon":"https:\/\/raw.githubusercontent.com\/jalajoninc\/tha\/main\/chanthaburi\/coffee-today-1\/10593751.jpg","price":"50","image":"https:\/\/images.deliveryhero.io\/image\/fd-th\/Products\/10593751.jpg","item":"Chocolate Frappe"},{"cat":"Milk Frappe","icon":"https:\/\/raw.githubusercontent.com\/jalajoninc\/tha\/main\/chanthaburi\/coffee-today-1\/10593754.jpg","price":"50","image":"https:\/\/images.deliveryhero.io\/image\/fd-th\/Products\/10593754.jpg","item":"Fresh Milk Frappe"},{"cat":"Milk Frappe","icon":"https:\/\/raw.githubusercontent.com\/jalajoninc\/tha\/main\/chanthaburi\/coffee-today-1\/10593753.jpg","price":"50","image":"https:\/\/images.deliveryhero.io\/image\/fd-th\/Products\/10593753.jpg","item":"Cocoa Frappe"},{"cat":"Milk Frappe","icon":"https:\/\/raw.githubusercontent.com\/jalajoninc\/tha\/main\/chanthaburi\/coffee-today-1\/10593752.jpg","price":"60","image":"https:\/\/images.deliveryhero.io\/image\/fd-th\/Products\/10593752.jpg","item":"Caramel Fresh Milk Frappe"},{"cat":"Fruit Juices","icon":"https:\/\/raw.githubusercontent.com\/jalajoninc\/tha\/main\/chanthaburi\/coffee-today-1\/10593755.jpg","price":"45","image":"https:\/\/images.deliveryhero.io\/image\/fd-th\/Products\/10593755.jpg","item":"Iced Pomegranate and Berry Soda"},{"cat":"Fruit Juices","icon":"https:\/\/raw.githubusercontent.com\/jalajoninc\/tha\/main\/chanthaburi\/coffee-today-1\/10593757.jpg","price":"45","image":"https:\/\/images.deliveryhero.io\/image\/fd-th\/Products\/10593757.jpg","item":"Iced Strawberry Juice"},{"cat":"Fruit Juices","icon":"https:\/\/raw.githubusercontent.com\/jalajoninc\/tha\/main\/chanthaburi\/coffee-today-1\/10593756.jpg","price":"45","image":"https:\/\/images.deliveryhero.io\/image\/fd-th\/Products\/10593756.jpg","item":"Iced Blueberry Juice"},{"cat":"Fruit Juices","icon":"https:\/\/raw.githubusercontent.com\/jalajoninc\/tha\/main\/chanthaburi\/coffee-today-1\/10593758.jpg","price":"45","image":"https:\/\/images.deliveryhero.io\/image\/fd-th\/Products\/10593758.jpg","item":"Iced Kiwi Juice"},{"cat":"Smoothie","icon":"https:\/\/raw.githubusercontent.com\/jalajoninc\/tha\/main\/chanthaburi\/coffee-today-1\/10593761.jpg","price":"50","image":"https:\/\/images.deliveryhero.io\/image\/fd-th\/Products\/10593761.jpg","item":"Yogurt Smoothie"},{"cat":"Smoothie","icon":"https:\/\/raw.githubusercontent.com\/jalajoninc\/tha\/main\/chanthaburi\/coffee-today-1\/10593759.jpg","price":"50","image":"https:\/\/images.deliveryhero.io\/image\/fd-th\/Products\/10593759.jpg","item":"Kiwi Smoothie"},{"cat":"Smoothie","icon":"https:\/\/raw.githubusercontent.com\/jalajoninc\/tha\/main\/chanthaburi\/coffee-today-1\/10593763.jpg","price":"50","image":"https:\/\/images.deliveryhero.io\/image\/fd-th\/Products\/10593763.jpg","item":"Blueberry Smoothie"},{"cat":"Smoothie","icon":"https:\/\/raw.githubusercontent.com\/jalajoninc\/tha\/main\/chanthaburi\/coffee-today-1\/10593764.jpg","price":"50","image":"https:\/\/images.deliveryhero.io\/image\/fd-th\/Products\/10593764.jpg","item":"Mixed Fruit Smoothie"},{"cat":"Smoothie","icon":"https:\/\/raw.githubusercontent.com\/jalajoninc\/tha\/main\/chanthaburi\/coffee-today-1\/10593762.jpg","price":"50","image":"https:\/\/images.deliveryhero.io\/image\/fd-th\/Products\/10593762.jpg","item":"Strawberry Smoothie"},{"cat":"Smoothie","icon":"https:\/\/raw.githubusercontent.com\/jalajoninc\/tha\/main\/chanthaburi\/coffee-today-1\/10593760.jpg","price":"55","image":"https:\/\/images.deliveryhero.io\/image\/fd-th\/Products\/10593760.jpg","item":"Mango Today Frape"},{"cat":"Take Home Bottle Beverages","dscr":"Glass bottle, with choices of topping available","icon":"https:\/\/raw.githubusercontent.com\/jalajoninc\/tha\/main\/chanthaburi\/coffee-today-1\/10593766.jpg","image":"https:\/\/images.deliveryhero.io\/image\/fd-th\/Products\/10593766.jpg","item":"Mocha","price":"55"},{"cat":"Take Home Bottle Beverages","dscr":"Glass bottle, with choices of topping available","icon":"https:\/\/raw.githubusercontent.com\/jalajoninc\/tha\/main\/chanthaburi\/coffee-today-1\/10593768.jpg","image":"https:\/\/images.deliveryhero.io\/image\/fd-th\/Products\/10593768.jpg","item":"Espresso","price":"55"},{"cat":"Take Home Bottle Beverages","dscr":"Glass bottle, with choices of topping available","icon":"https:\/\/raw.githubusercontent.com\/jalajoninc\/tha\/main\/chanthaburi\/coffee-today-1\/10593770.jpg","image":"https:\/\/images.deliveryhero.io\/image\/fd-th\/Products\/10593770.jpg","item":"Today Coffee","price":"55"},{"cat":"Take Home Bottle Beverages","dscr":"Glass bottle, with choices of topping available","icon":"https:\/\/raw.githubusercontent.com\/jalajoninc\/tha\/main\/chanthaburi\/coffee-today-1\/10593775.jpg","image":"https:\/\/images.deliveryhero.io\/image\/fd-th\/Products\/10593775.jpg","item":"Latte","price":"55"},{"cat":"Take Home Bottle Beverages","dscr":"Glass bottle, with choices of topping available","icon":"https:\/\/raw.githubusercontent.com\/jalajoninc\/tha\/main\/chanthaburi\/coffee-today-1\/10593774.jpg","image":"https:\/\/images.deliveryhero.io\/image\/fd-th\/Products\/10593774.jpg","item":"Cappuccino","price":"55"},{"cat":"Take Home Bottle Beverages","dscr":"Glass bottle, with choices of topping available","icon":"https:\/\/raw.githubusercontent.com\/jalajoninc\/tha\/main\/chanthaburi\/coffee-today-1\/10593767.jpg","image":"https:\/\/images.deliveryhero.io\/image\/fd-th\/Products\/10593767.jpg","item":"Espuccino","price":"55"},{"cat":"Take Home Bottle Beverages","dscr":"Glass bottle, with choices of topping available","icon":"https:\/\/raw.githubusercontent.com\/jalajoninc\/tha\/main\/chanthaburi\/coffee-today-1\/10593772.jpg","image":"https:\/\/images.deliveryhero.io\/image\/fd-th\/Products\/10593772.jpg","item":"Thai Black Tea","price":"55"},{"cat":"Take Home Bottle Beverages","dscr":"Glass bottle, with choices of topping available","icon":"https:\/\/raw.githubusercontent.com\/jalajoninc\/tha\/main\/chanthaburi\/coffee-today-1\/10593772.jpg","image":"https:\/\/images.deliveryhero.io\/image\/fd-th\/Products\/10593772.jpg","item":"Green Tea with Milk","price":"55"},{"cat":"Take Home Bottle Beverages","dscr":"Glass bottle, with choices of topping available","icon":"https:\/\/raw.githubusercontent.com\/jalajoninc\/tha\/main\/chanthaburi\/coffee-today-1\/10593773.jpg","image":"https:\/\/images.deliveryhero.io\/image\/fd-th\/Products\/10593773.jpg","item":"Americano","price":"55"},{"cat":"Take Home Bottle Beverages","dscr":"Glass bottle, with choices of topping available","icon":"https:\/\/raw.githubusercontent.com\/jalajoninc\/tha\/main\/chanthaburi\/coffee-today-1\/10593773.jpg","image":"https:\/\/images.deliveryhero.io\/image\/fd-th\/Products\/10593773.jpg","item":"Thai Tea","price":"55"},{"cat":"Take Home Bottle Beverages","dscr":"Glass bottle, with choices of topping available","icon":"https:\/\/raw.githubusercontent.com\/jalajoninc\/tha\/main\/chanthaburi\/coffee-today-1\/10593776.jpg","image":"https:\/\/images.deliveryhero.io\/image\/fd-th\/Products\/10593776.jpg","item":"Chocolate","price":"55"},{"cat":"Take Home Bottle Beverages","dscr":"Glass bottle, with choices of topping available","icon":"https:\/\/raw.githubusercontent.com\/jalajoninc\/tha\/main\/chanthaburi\/coffee-today-1\/10593765.jpg","image":"https:\/\/images.deliveryhero.io\/image\/fd-th\/Products\/10593765.jpg","item":"Cocoa","price":"55"},{"cat":"Bag Beverages","dscr":"500 ml. With choices of topping available","icon":"https:\/\/raw.githubusercontent.com\/jalajoninc\/tha\/main\/chanthaburi\/coffee-today-1\/10593777.jpg","image":"https:\/\/images.deliveryhero.io\/image\/fd-th\/Products\/10593777.jpg","item":"Thai Tea","price":"139"},{"cat":"Bag Beverages","dscr":"500 ml. With choices of topping available","icon":"https:\/\/raw.githubusercontent.com\/jalajoninc\/tha\/main\/chanthaburi\/coffee-today-1\/10593780.jpg","image":"https:\/\/images.deliveryhero.io\/image\/fd-th\/Products\/10593780.jpg","item":"Cocoa","price":"139"},{"cat":"Bag Beverages","dscr":"500 ml. With choices of topping available","icon":"https:\/\/raw.githubusercontent.com\/jalajoninc\/tha\/main\/chanthaburi\/coffee-today-1\/10593779.jpg","image":"https:\/\/images.deliveryhero.io\/image\/fd-th\/Products\/10593779.jpg","item":"Green Tea with Milk","price":"139"},{"cat":"Bag Beverages","dscr":"500 ml. With choices of topping available","icon":"https:\/\/raw.githubusercontent.com\/jalajoninc\/tha\/main\/chanthaburi\/coffee-today-1\/10593781.jpg","image":"https:\/\/images.deliveryhero.io\/image\/fd-th\/Products\/10593781.jpg","item":"Thai Iced Coffee","price":"139"},{"cat":"Bag Beverages","dscr":"500 ml. With choices of topping available","icon":"https:\/\/raw.githubusercontent.com\/jalajoninc\/tha\/main\/chanthaburi\/coffee-today-1\/10593778.jpg","image":"https:\/\/images.deliveryhero.io\/image\/fd-th\/Products\/10593778.jpg","item":"Americano","price":"139"},{"cat":"Desserts","icon":"https:\/\/raw.githubusercontent.com\/jalajoninc\/tha\/main\/chanthaburi\/coffee-today-1\/10593708.jpg","price":"30","image":"https:\/\/images.deliveryhero.io\/image\/fd-th\/Products\/10593708.jpg","item":"Caramel Waffle"},{"cat":"Desserts","icon":"https:\/\/raw.githubusercontent.com\/jalajoninc\/tha\/main\/chanthaburi\/coffee-today-1\/10593709.jpg","price":"49","image":"https:\/\/images.deliveryhero.io\/image\/fd-th\/Products\/10593709.jpg","item":"Dark Chocolate Cracker"},{"cat":"Sides","dscr":"5 sachets","icon":"https:\/\/raw.githubusercontent.com\/jalajoninc\/tha\/main\/chanthaburi\/coffee-today-1\/10593707.jpg","image":"https:\/\/images.deliveryhero.io\/image\/fd-th\/Products\/10593707.jpg","item":"Drip Coffee","price":"120"}]