[{"cat":"House Specials","price":"45","item":"Dark Brownie","dscr":"Cocoa frappe with chocolate sauce With choices of topping available"},{"cat":"House Specials","price":"35","item":"Volcano Ovaltine","dscr":"Ovaltine powder and condensed milk With choices of topping available"},{"cat":"House Specials","price":"45","item":"Pony Milk","dscr":"Fresh milk frappe separate pink and blue level, whipped cream , condensed milk, and Ojo waffle. With choices of topping available"},{"cat":"House Specials","price":"45","item":"Pastel Milk","dscr":"Mixed fresh milk with pink blue and yellow syrup With choices of topping available"},{"cat":"House Specials","price":"45","item":"Caramel Cornflakes Frappe","dscr":"With choices of topping available"},{"cat":"House Specials","price":"45","item":"Vanila Pastel","dscr":"Fresh milk frappe separate pink and blue level, whipped cream, and rainbow sprinkle With choices of topping available"},{"cat":"House Specials","price":"35","item":"Yakult Pipo","dscr":"With choices of topping available"},{"cat":"House Specials","price":"40","item":"Brown Sugar Milk","dscr":"With choices of topping available"},{"cat":"House Specials","price":"45","item":"Caramel with Oreo Milk","dscr":"With choices of topping available"},{"cat":"House Specials","price":"45","item":"Thai Milk Tea with Oreo","dscr":"With choices of topping available"},{"cat":"House Specials","price":"45","item":"Green tea with Oreo","dscr":"With choices of topping available"},{"cat":"House Specials","price":"45","item":"Thai Milk Tea with Sweet Egg Floss","dscr":"With choices of topping available"},{"cat":"House Specials","price":"35","item":"Two Toned Milk Tea","dscr":"Taro milk and pink milk separate level With choices of topping available"},{"cat":"House Specials","price":"30","item":"Lava Thai Milk Tea","dscr":"Thai milk tea with chocolate With choices of topping available"},{"price":"15","cat":"Desserts","item":"Butter and Condensed Milk Toast with Sugar"}]